h264_profile_level_id/__init__.py
h264_profile_level_id/__version__.py
h264_profile_level_id/core.py
h264_profile_level_id-1.0.0.dist-info/METADATA
h264_profile_level_id-1.0.0.dist-info/WHEEL
h264_profile_level_id-1.0.0.dist-info/top_level.txt
h264_profile_level_id-1.0.0.dist-info/RECORD
